hundun/__init__.py
hundun/equations/__init__.py
hundun/equations/henon.py
hundun/equations/logistic.py
hundun/equations/lorenz.py
hundun/exploration/__init__.py
hundun/exploration/_afn.py
hundun/exploration/_autocorrelation.py
hundun/exploration/_box3.py
hundun/exploration/_fnn.py
hundun/exploration/_gp.py
hundun/exploration/_mutualinfo.py
hundun/exploration/_recurrenceplot.py
hundun/exploration/_utils.py
hundun/exploration/_wayland.py
hundun/lyapunov/__init__.py
hundun/lyapunov/_func.py
hundun/lyapunov/_les_difference.py
hundun/lyapunov/_les_differential.py
hundun/systems/__init__.py
hundun/systems/_difference.py
hundun/systems/_differential.py
hundun/systems/_solver.py
hundun/systems/_sync.py
hundun/systems/_systems.py
hundun/systems/_tu.py
hundun/utils/__init__.py
hundun/utils/_draw.py
hundun-0.1.39.dist-info/LICENSE.txt
hundun-0.1.39.dist-info/METADATA
hundun-0.1.39.dist-info/WHEEL
hundun-0.1.39.dist-info/top_level.txt
hundun-0.1.39.dist-info/RECORD
