Metadata-Version: 2.1
Name: hundun
Version: 0.1.39
Summary: hundun is a python library for the exploration of chaos.
Author-email: kosh <llllbxg@gmail.com>
License: MIT License
Project-URL: repository, http://github.com/llbxg/hundun
Classifier: Topic :: Scientific/Engineering :: Physics
Requires-Python: >=3.8
License-File: LICENSE.txt
Requires-Dist: scipy
Requires-Dist: matplotlib
Requires-Dist: numpy
Provides-Extra: dev
Requires-Dist: flake8 ; extra == 'dev'
Requires-Dist: setuptools-scm ; extra == 'dev'
Requires-Dist: wheel ; extra == 'dev'
Requires-Dist: build ; extra == 'dev'
Requires-Dist: twine ; extra == 'dev'
